jeecf/__init__.py
jeecf/command.py
jeecf/exceptions.py
jeecf/jeecf.py
jeecf_cli-0.0.3.dist-info/LICENSE
jeecf_cli-0.0.3.dist-info/METADATA
jeecf_cli-0.0.3.dist-info/WHEEL
jeecf_cli-0.0.3.dist-info/entry_points.txt
jeecf_cli-0.0.3.dist-info/top_level.txt
jeecf_cli-0.0.3.dist-info/RECORD
