Metadata-Version: 2.1
Name: jeecf-cli
Version: 0.0.3
Summary: Jeecf client toolbox
Home-page: https://github.com/cgfly/jeecf-cli
Author: tcitry
Author-email: tcitry@gmail.com
License: Apache License 2.0
Keywords: cloud factory client commandline
Platform: UNKNOWN
Requires-Dist: requests
Requires-Dist: click
